README.md
pyproject.toml
setup.py
tests/__init__.py
tests/test_cls_simple.py
tests/test_cls_strict.py
tests/test_pipe.py
tests/test_url_scrapper.py
web_page_cls/__init__.py
web_page_cls/annotator.py
web_page_cls/describer.py
web_page_cls/get_stat.py
web_page_cls/pipeline.py
web_page_cls.egg-info/PKG-INFO
web_page_cls.egg-info/SOURCES.txt
web_page_cls.egg-info/dependency_links.txt
web_page_cls.egg-info/requires.txt
web_page_cls.egg-info/top_level.txt
web_page_cls/classifiers/__init__.py
web_page_cls/classifiers/classifier_base.py
web_page_cls/classifiers/classifier_simple.py
web_page_cls/classifiers/classifier_strict_ollama.py
web_page_cls/classifiers/classifier_strict_openai.py
web_page_cls/classifiers/cls_prompts.py
web_page_cls/classifiers/config.py
web_page_cls/datasets/__init__.py
web_page_cls/datasets/dataset_reader.py
web_page_cls/datasets/web_page_examples.py
web_page_cls/datasets/website_classification.json
web_page_cls/lang_detectors/__init__.py
web_page_cls/lang_detectors/code2lang.json
web_page_cls/lang_detectors/fasttext_custom.py
web_page_cls/lang_detectors/iso-639-3.tab
web_page_cls/lang_detectors/json_loader.py
web_page_cls/lang_detectors/lang_detector.py
web_page_cls/utils/__init__.py
web_page_cls/utils/chunker.py
web_page_cls/utils/cleaner.py
web_page_cls/utils/html2md.py
web_page_cls/utils/image_cache_handler.py
web_page_cls/utils/io.py
web_page_cls/utils/metrics.py
web_page_cls/utils/prompts.py
web_page_cls/utils/url2html.py