Metadata-Version: 2.1
Name: web-page-cls
Version: 0.0.7
Summary: Web page LLM classifier and summarizer
Home-page: UNKNOWN
Author: Batman
Author-email: batman@c.com
License: MIT License
Platform: UNKNOWN
